LICENSE.md
MANIFEST.in
README.md
package.json
setup.py
dash_html_components/A.py
dash_html_components/Abbr.py
dash_html_components/Acronym.py
dash_html_components/Address.py
dash_html_components/Area.py
dash_html_components/Article.py
dash_html_components/Aside.py
dash_html_components/Audio.py
dash_html_components/B.py
dash_html_components/Base.py
dash_html_components/Basefont.py
dash_html_components/Bdi.py
dash_html_components/Bdo.py
dash_html_components/Big.py
dash_html_components/Blink.py
dash_html_components/Blockquote.py
dash_html_components/Br.py
dash_html_components/Button.py
dash_html_components/Canvas.py
dash_html_components/Caption.py
dash_html_components/Center.py
dash_html_components/Cite.py
dash_html_components/Code.py
dash_html_components/Col.py
dash_html_components/Colgroup.py
dash_html_components/Command.py
dash_html_components/Content.py
dash_html_components/Data.py
dash_html_components/Datalist.py
dash_html_components/Dd.py
dash_html_components/Del.py
dash_html_components/Details.py
dash_html_components/Dfn.py
dash_html_components/Dialog.py
dash_html_components/Div.py
dash_html_components/Dl.py
dash_html_components/Dt.py
dash_html_components/Element.py
dash_html_components/Em.py
dash_html_components/Embed.py
dash_html_components/Fieldset.py
dash_html_components/Figcaption.py
dash_html_components/Figure.py
dash_html_components/Font.py
dash_html_components/Footer.py
dash_html_components/Form.py
dash_html_components/Frame.py
dash_html_components/Frameset.py
dash_html_components/H1.py
dash_html_components/H2.py
dash_html_components/H3.py
dash_html_components/H4.py
dash_html_components/H5.py
dash_html_components/H6.py
dash_html_components/Header.py
dash_html_components/Hgroup.py
dash_html_components/Hr.py
dash_html_components/I.py
dash_html_components/Iframe.py
dash_html_components/Img.py
dash_html_components/Ins.py
dash_html_components/Isindex.py
dash_html_components/Kbd.py
dash_html_components/Keygen.py
dash_html_components/Label.py
dash_html_components.egg-info/PKG-INFO
dash_html_components.egg-info/SOURCES.txt
dash_html_components.egg-info/dependency_links.txt
dash_html_components.egg-info/top_level.txt