Metadata-Version: 2.1
Name: dash_html_components
Version: 1.1.3
Summary: Vanilla HTML components for Dash
Home-page: https://github.com/plotly/dash-html-components
Author: Chris Parmer <chris@plotly.com>
Author-email: chris@plotly.com
License: MIT
Platform: UNKNOWN
